{
    "vdsp_op_type": "RGB_RESIZE_CVTCOLOR_NORMALIZATION_TENSORIZATION_U8",
    "config": [
        {
            "Property": "iimage_format",
            "DType": "UINT_32",
            "ParamType": "ELEMENT",
            "Value": "RGB_PLANAR"
        },
        {
            "Property": "iimage_width",
            "DType": "INT",
            "ParamType": "ELEMENT",
            "Value": 320
        },
        {
            "Property": "iimage_height",
            "DType": "INT",
            "ParamType": "ELEMENT",
            "Value": 320
        },
        {
            "Property": "iimage_width_pitch",
            "DType": "UINT_32",
            "ParamType": "ELEMENT",
            "Value": 320
        },
        {
            "Property": "iimage_height_pitch",
            "DType": "UINT_32",
            "ParamType": "ELEMENT",
            "Value": 320
        },
        {
            "Property": "oimage_width",
            "DType": "INT",
            "ParamType": "ELEMENT",
            "Value": 320
        },
        {
            "Property": "oimage_height",
            "DType": "INT",
            "ParamType": "ELEMENT",
            "Value": 320
        },
        {
            "Property": "meanr",
            "DType": "UINT_16",
            "ParamType": "ELEMENT",
            "Value": 14275
        },
        {
            "Property": "meang",
            "DType": "UINT_16",
            "ParamType": "ELEMENT",
            "Value": 14156
        },
        {
            "Property": "meanb",
            "DType": "UINT_16",
            "ParamType": "ELEMENT",
            "Value": 13951
        },
        {
            "Property": "stdr",
            "DType": "UINT_16",
            "ParamType": "ELEMENT",
            "Value": 13140
        },
        {
            "Property": "stdg",
            "DType": "UINT_16",
            "ParamType": "ELEMENT",
            "Value": 13099
        },
        {
            "Property": "stdb",
            "DType": "UINT_16",
            "ParamType": "ELEMENT",
            "Value": 13107
        },
        {
            "Property": "norma_type",
            "DType": "INT",
            "ParamType": "ELEMENT",
            "Value": "DIV255_MINUSMEAN_DIVSTD"
        },
        {
            "Property": "resize_type",
            "DType": "INT",
            "ParamType": "ELEMENT",
            "Value": "BILINEAR_CV"
        },
        {
            "Property": "color_cvt_code",
            "DType": "UINT_16",
            "ParamType": "ELEMENT",
            "Value": "COLOR_NO_CHANGE"
        },
        {
            "Property": "color_space",
            "DType": "UINT_16",
            "ParamType": "ELEMENT",
            "Value": "COLOR_SPACE_BT709"
        }
    ]
}
